setup.py
santoshcrleasetestpackage/__init__.py
santoshcrleasetestpackage.egg-info/PKG-INFO
santoshcrleasetestpackage.egg-info/SOURCES.txt
santoshcrleasetestpackage.egg-info/dependency_links.txt
santoshcrleasetestpackage.egg-info/top_level.txt