Metadata-Version: 2.4
Name: santoshcrleasetestpackage
Version: 0.1.0
Summary: This is a demo python package by santosh
Author: Santosh Acharya
Requires-Python: >=3.8
Dynamic: author
Dynamic: requires-python
Dynamic: summary
